{ 
    "_id" : ObjectId("5c40c20b3249af2aa863c16d"), 
    "Title" : "Въглехидрати", 
    "Description" : "Всичко за въглехидратите в Зоната", 
    "Topics" : [
        {
            "index" : NumberInt(0), 
            "title" : "Общо за протеините"
        }, 
        {
            "index" : NumberInt(1), 
            "title" : "Още"
        }
    ], 
    "Text" : [
        {
            "index" : NumberInt(0), 
            "text" : "ajfhvjhu htbb hhb rgbh nskajfhvjhu htbb hhb rgbh nskajfhvjhu htbb hhb rgbh nskajfhvjhu htbb hhb rgbh nskajfhvjhu htbb hhb rgbh nskajfhvjhu htbb hhb rgbh nskajfhvjhu htbb hhb rgbh nskajfhvjhu htbb hhb rgbh nskajfhvjhu htbb hhb rgbh nskajfhvjhu htbb hhb rgbh nskajfhvjhu htbb hhb rgbh nskajfhvjhu htbb hhb rgbh nskajfhvjhu htbb hhb rgbh nskajfhvjhu htbb hhb rgbh nskajfhvjhu htbb hhb rgbh nskajfhvjhu htbb hhb rgbh nskajfhvjhu htbb hhb rgbh nskajfhvjhu htbb hhb rgbh nskajfhvjhu htbb hhb rgbh nskajfhvjhu htbb hhb rgbh nskajfhvjhu htbb hhb rgbh nskajfhvjhu htbb hhb rgbh nskajfhvjhu htbb hhb rgbh nskajfhvjhu htbb hhb rgbh nskajfhvjhu htbb hhb rgbh nskajfhvjhu htbb hhb rgbh nskajfhvjhu htbb hhb rgbh nskajfhvjhu htbb hhb rgbh nskajfhvjhu htbb hhb rgbh nskajfhvjhu htbb hhb rgbh nskajfhvjhu htbb hhb rgbh nskajfhvjhu htbb hhb rgbh nskajfhvjhu htbb hhb rgbh nskajfhvjhu htbb hhb rgbh nskajfhvjhu htbb hhb rgbh nskajfhvjhu htbb hhb rgbh nskajfhvjhu htbb hhb rgbh nskajfhvjhu htbb hhb rgbh nskajfhvjhu htbb hhb rgbh nskajfhvjhu htbb hhb rgbh nskajfhvjhu htbb hhb rgbh nskajfhvjhu htbb hhb rgbh nskajfhvjhu htbb hhb rgbh nskajfhvjhu htbb hhb rgbh nskajfhvjhu htbb hhb rgbh nskajfhvjhu htbb hhb rgbh nskajfhvjhu htbb hhb rgbh nskajfhvjhu htbb hhb rgbh nskajfhvjhu htbb hhb rgbh nskajfhvjhu htbb hhb rgbh nskajfhvjhu htbb hhb rgbh nskajfhvjhu htbb hhb rgbh nskajfhvjhu htbb hhb rgbh nskajfhvjhu htbb hhb rgbh nskajfhvjhu htbb hhb rgbh nskajfhvjhu htbb hhb rgbh nskajfhvjhu htbb hhb rgbh nskajfhvjhu htbb hhb rgbh nskajfhvjhu htbb hhb rgbh nskajfhvjhu htbb hhb rgbh nskajfhvjhu htbb hhb rgbh nskajfhvjhu htbb hhb rgbh nskajfhvjhu htbb hhb rgbh nskajfhvjhu htbb hhb rgbh nskajfhvjhu htbb hhb rgbh nskajfhvjhu htbb hhb rgbh nskajfhvjhu htbb hhb rgbh nskajfhvjhu htbb hhb rgbh nskajfhvjhu htbb hhb rgbh nskajfhvjhu htbb hhb rgbh nskajfhvjhu htbb hhb rgbh nskajfhvjhu htbb hhb rgbh nskajfhvjhu htbb hhb rgbh nskajfhvjhu htbb hhb rgbh nskajfhvjhu htbb hhb rgbh nskajfhvjhu htbb hhb rgbh nskajfhvjhu htbb hhb rgbh nskajfhvjhu htbb hhb rgbh nskajfhvjhu htbb hhb rgbh nskajfhvjhu htbb hhb rgbh nskajfhvjhu htbb hhb rgbh nskajfhvjhu htbb hhb rgbh nskajfhvjhu htbb hhb rgbh nskajfhvjhu htbb hhb rgbh nskajfhvjhu htbb hhb rgbh nskajfhvjhu htbb hhb rgbh nskajfhvjhu htbb hhb rgbh nskajfhvjhu htbb hhb rgbh nskajfhvjhu htbb hhb rgbh nskajfhvjhu htbb hhb rgbh nskajfhvjhu htbb hhb rgbh nskajfhvjhu htbb hhb rgbh nskajfhvjhu htbb hhb rgbh nskajfhvjhu htbb hhb rgbh nskajfhvjhu htbb hhb rgbh nskajfhvjhu htbb hhb rgbh nskajfhvjhu htbb hhb rgbh nskajfhvjhu htbb hhb rgbh nskajfhvjhu htbb hhb rgbh nskajfhvjhu htbb hhb rgbh nskajfhvjhu htbb hhb rgbh nskajfhvjhu htbb hhb rgbh nskajfhvjhu htbb hhb rgbh nskajfhvjhu htbb hhb rgbh nskajfhvjhu htbb hhb rgbh nskajfhvjhu htbb hhb rgbh nskajfhvjhu htbb hhb rgbh nskajfhvjhu htbb hhb rgbh nskajfhvjhu htbb hhb rgbh nskajfhvjhu htbb hhb rgbh nskajfhvjhu htbb hhb rgbh nskajfhvjhu htbb hhb rgbh nskajfhvjhu htbb hhb rgbh nskajfhvjhu htbb hhb rgbh nskajfhvjhu htbb hhb rgbh nskajfhvjhu htbb hhb rgbh nskajfhvjhu htbb hhb rgbh nskajfhvjhu htbb hhb rgbh nskajfhvjhu htbb hhb rgbh nskajfhvjhu htbb hhb rgbh nskajfhvjhu htbb hhb rgbh nskajfhvjhu htbb hhb rgbh nskajfhvjhu htbb hhb rgbh nskajfhvjhu htbb hhb rgbh nskajfhvjhu htbb hhb rgbh nskajfhvjhu htbb hhb rgbh nskajfhvjhu htbb hhb rgbh nskajfhvjhu htbb hhb rgbh nskajfhvjhu htbb hhb rgbh nskajfhvjhu htbb hhb rgbh nskajfhvjhu htbb hhb rgbh nskajfhvjhu htbb hhb rgbh nskajfhvjhu htbb hhb rgbh nskajfhvjhu htbb hhb rgbh nskajfhvjhu htbb hhb rgbh nskajfhvjhu htbb hhb rgbh nskajfhvjhu htbb hhb rgbh nskajfhvjhu htbb hhb rgbh nskajfhvjhu htbb hhb rgbh nskajfhvjhu htbb hhb rgbh nskajfhvjhu htbb hhb rgbh nskajfhvjhu htbb hhb rgbh nskajfhvjhu htbb hhb rgbh nskajfhvjhu htbb hhb rgbh nskajfhvjhu htbb hhb rgbh nskajfhvjhu htbb hhb rgbh nskajfhvjhu htbb hhb rgbh nskajfhvjhu htbb hhb rgbh nskajfhvjhu htbb hhb rgbh nskajfhvjhu htbb hhb rgbh nskajfhvjhu htbb hhb rgbh nskajfhvjhu htbb hhb rgbh nskajfhvjhu htbb hhb rgbh nskajfhvjhu htbb hhb rgbh nskajfhvjhu htbb hhb rgbh nskajfhvjhu htbb hhb rgbh nskajfhvjhu htbb hhb rgbh nskajfhvjhu htbb hhb rgbh nskajfhvjhu htbb hhb rgbh nskajfhvjhu htbb hhb rgbh nskajfhvjhu htbb hhb rgbh nskajfhvjhu htbb hhb rgbh nskajfhvjhu htbb hhb rgbh nskajfhvjhu htbb hhb rgbh nskajfhvjhu htbb hhb rgbh nskajfhvjhu htbb hhb rgbh nskajfhvjhu htbb hhb rgbh nskajfhvjhu htbb hhb rgbh nsk"
        }, 
        {
            "index" : NumberInt(1), 
            "text" : "gsershtk"
        }
    ]
}
{ 
    "_id" : ObjectId("5c41edfd3249af0dd44d1681"), 
    "Title" : "Протеини", 
    "Keywords" : "протеини, видове, белтъци", 
    "Description" : "Всичко за протеините", 
    "Text" : [

    ], 
    "Topics" : ""
}
